periodic_table/__init__.py
periodic_table/ptable.py
sadhu_periodic_table-0.1.dist-info/DESCRIPTION.rst
sadhu_periodic_table-0.1.dist-info/METADATA
sadhu_periodic_table-0.1.dist-info/RECORD
sadhu_periodic_table-0.1.dist-info/WHEEL
sadhu_periodic_table-0.1.dist-info/metadata.json
sadhu_periodic_table-0.1.dist-info/top_level.txt
