Metadata-Version: 2.0
Name: sadhu-periodic-table
Version: 0.1
Summary: chemistry symbols and name
Home-page: https://github.com/cloudsadhu/dojo_rules/ravi_periodic_table
Author: cloudsadhu
Author-email: cloudsadhu@gmail.com.com
License: MIT
Platform: UNKNOWN
